{
    "12345": {
        "crm": "12345",
        "nome": "Strange ",
        "email": "strange@mail",
        "especialidade": "Cardiologia",
        "clinica": "New Heart"
    },
    "1": {
        "crm": "1",
        "nome": "Ray",
        "email": "ray@gmail",
        "especialidade": "Neurologia",
        "clinica": "Dunder Mifflin"
    },
    "34345": {
        "crm": "34345",
        "nome": "Jhon",
        "email": "jhon@hotmail",
        "especialidade": "Cardiologia",
        "clinica": "Santa Rita "
    },
    "23233": {
        "crm": "23233",
        "nome": "Carlos",
        "email": "carl@yahoo",
        "especialidade": "Neurologia",
        "clinica": "Albert"
    },
    "01000": {
        "crm": "01000",
        "nome": "Amelia",
        "email": "mel@gmail",
        "especialidade": "Cardiologia",
        "clinica": "S\u00e3o Jos\u00e9"
    }
}